{
  "ScheduleActions": [],
  "PrimaryActions": [
    {
      "Name": "wait_action",
      "MinTime": 0,
      "Hidden": false,
      "Requirements": {},
      "Effects": {}
    },
    {
      "Name": "travel_action",
      "MinTime": 0,
      "Hidden": false,
      "Requirements": {},
      "Effects": {}
    },
    {
      "Name": "Escape the heat",
      "MinTime": 20,
      "Hidden": false,
      "Requirements": {
        "Location Requirements": [
          {
            "HasAllOf": [
              "Building"
            ],
            "HasOneOrMoreOf": [],
            "HasNoneOf": []
          }
        ]
      },
      "Effects": {
        "physical": 1,
		"social": -1
      }
    },
    {
      "Name": "Eat",
      "MinTime": 40,
      "Hidden": false,
      "Requirements": {
        "Location Requirements": [
          {
            "HasAllOf": [
              "Restaurant"
            ],
            "HasOneOrMoreOf": [],
            "HasNoneOf": []
          }
        ]
      },
      "Effects": {
        "physical": 3,
		"financial": -1
      }
    },
    {
      "Name": "Eat with friend",
      "MinTime": 60,
      "Hidden": false,
      "Requirements": {
        "Location Requirements": [
          {
            "HasAllOf": [
              "Restaurant"
            ],
            "HasOneOrMoreOf": [],
            "HasNoneOf": []
          }
        ],
        "People Requirements": [
          {
            "RelationshipsPresent": [
              "Friend"
            ],
            "MinNumPeople": 2,
            "MaxNumPeople": 60,
            "SpecificPeoplePresent": [],
            "SpecificPeopleAbsent": [],
            "RelationshipsAbsent": []
          }
        ]
      },
      "Effects": {
        "physical": 2,
        "social": 2,
		"financial": -1
      }
    },
    {
      "Name": "Work remote",
      "MinTime": 60,
      "Hidden": false,
      "Requirements": {
        "Location Requirements": [
          {
            "HasAllOf": [
              "has:Computer"
            ],
            "HasOneOrMoreOf": [],
            "HasNoneOf": []
          }
        ]
      },
      "Effects": {
        "accomplishment": 2,
        "financial": 1,
		"emotional": -1
      }
    }
  ]
}